nits/__init__.py
nits/cast.py
nits/clui.py
nits/doit.py
nits/file.py
nits/repeatit.py
nits/reporter.py
nits/time.py
nits-0.19.dist-info/LICENSE.txt
nits-0.19.dist-info/METADATA
nits-0.19.dist-info/WHEEL
nits-0.19.dist-info/entry_points.txt
nits-0.19.dist-info/top_level.txt
nits-0.19.dist-info/RECORD
