Metadata-Version: 2.1
Name: nits
Version: 0.19
Summary: Nits is small collection of classes, functions and utilities for tweaking python syntaxx
Home-page: https://github.com/scott-howard-james/nits
Author: Scott Howard James
License: UNKNOWN
Keywords: container functional composition relation
Platform: UNKNOWN
Classifier: Development Status :: 3 - Alpha
Classifier: Intended Audience :: Developers
Classifier: Topic :: Software Development
Classifier: License :: OSI Approved :: Apache Software License
Classifier: Programming Language :: Python :: 3.4
Classifier: Programming Language :: Python :: 3.5
Classifier: Programming Language :: Python :: 3.6
Classifier: Programming Language :: Python :: 3.7
Requires-Python: >=3.4
Requires-Dist: docopt
